menu_zerobeef/__init__.py
menu_zerobeef/data.py
menu_zerobeef/example.py
menu_zerobeef/main.py
menu_zerobeef/menu.py
menu_zerobeef/setup.py
menu_zerobeef-0.2.dist-info/LICENSE.md
menu_zerobeef-0.2.dist-info/METADATA
menu_zerobeef-0.2.dist-info/WHEEL
menu_zerobeef-0.2.dist-info/top_level.txt
menu_zerobeef-0.2.dist-info/RECORD
