Metadata-Version: 2.1
Name: menu-zerobeef
Version: 0.2
Summary: A simple menu program for command line enthusiasts made possible using curses
Author-email: Erik <zerobeef@icloud.com>
License: MIT License        
Project-URL: Homepage, https://github.com/erikkamph/project_menu
Project-URL: Bug Tracker, https://github.com/erikkamph/project_menu/issues
Classifier: Programming Language :: Python :: 3
Classifier: License :: OSI Approved :: MIT License
Classifier: Operating System :: OS Independent
Requires-Python: >=3.7
License-File: LICENSE.md
